gpmpy/__init__.py
gpmpy/gpm.py
gpmpy-0.0.2.dist-info/METADATA
gpmpy-0.0.2.dist-info/WHEEL
gpmpy-0.0.2.dist-info/top_level.txt
gpmpy-0.0.2.dist-info/RECORD
