Metadata-Version: 2.1
Name: gpmpy
Version: 0.0.2
Summary: a library for DS CAA Developer
Author: zyd
License: MIT License
Keywords: gpm
Platform: any
